sstc_dp/__init__.py
sstc_dp/version.py
sstc_dp-0.1.4.dist-info/METADATA
sstc_dp-0.1.4.dist-info/WHEEL
sstc_dp-0.1.4.dist-info/RECORD
